{"rows": 5, "cols": 5, "side_length": 0.5, "wall_cell_ratio": 0.1, "cells": {"0_0": {"N": true, "S": true, "E": false, "W": true}, "0_1": {"N": false, "S": true, "E": false, "W": true}, "0_2": {"N": true, "S": false, "E": false, "W": true}, "0_3": {"N": false, "S": true, "E": false, "W": false}, "0_4": {"N": true, "S": false, "E": false, "W": true}, "1_0": {"N": true, "S": true, "E": false, "W": false}, "1_1": {"N": true, "S": true, "E": true, "W": false}, "1_2": {"N": true, "S": true, "E": false, "W": false}, "1_3": {"N": true, "S": true, "E": false, "W": false}, "1_4": {"N": true, "S": true, "E": false, "W": false}, "2_0": {"N": false, "S": true, "E": true, "W": false}, "2_1": {"N": true, "S": false, "E": false, "W": true}, "2_2": {"N": true, "S": true, "E": false, "W": false}, "2_3": {"N": true, "S": true, "E": false, "W": false}, "2_4": {"N": true, "S": true, "E": false, "W": false}, "3_0": {"N": false, "S": true, "E": false, "W": true}, "3_1": {"N": true, "S": false, "E": true, "W": false}, "3_2": {"N": false, "S": true, "E": true, "W": false}, "3_3": {"N": true, "S": false, "E": true, "W": false}, "3_4": {"N": true, "S": true, "E": false, "W": false}, "4_0": {"N": false, "S": true, "E": true, "W": false}, "4_1": {"N": false, "S": false, "E": true, "W": true}, "4_2": {"N": false, "S": false, "E": true, "W": true}, "4_3": {"N": false, "S": false, "E": true, "W": true}, "4_4": {"N": true, "S": false, "E": true, "W": false}}}